fedapay_connector/__init__.py
fedapay_connector/connector.py
fedapay_connector/db_models.py
fedapay_connector/enums.py
fedapay_connector/event.py
fedapay_connector/event_storage.py
fedapay_connector/exceptions.py
fedapay_connector/integration.py
fedapay_connector/maps.py
fedapay_connector/server.py
fedapay_connector/types.py
fedapay_connector/utils.py
fedapay_connector/integrations/__init__.py
fedapay_connector/integrations/balances.py
fedapay_connector/integrations/currencies.py
fedapay_connector/integrations/events.py
fedapay_connector/integrations/logs.py
fedapay_connector/integrations/transactions.py
fedapay_connector/integrations/webhooks.py
fedapay_connector/models/__init__.py
fedapay_connector/models/base.py
fedapay_connector/models/models.py
fedapay_connector-2.0.2.dist-info/METADATA
fedapay_connector-2.0.2.dist-info/WHEEL
fedapay_connector-2.0.2.dist-info/licenses/LICENSE
fedapay_connector-2.0.2.dist-info/RECORD
