Metadata-Version: 2.4
Name: fedapay_connector
Version: 2.0.2
Summary: Un client asynchrone robuste pour l'API FedaPay, offrant une gestion automatisée des paiements avec support complet des webhooks.
Project-URL: Homepage, https://github.com/Dasero197/fedapay_connector
Project-URL: Issues, https://github.com/Dasero197/fedapay_connector/issues
Project-URL: Changelog, https://github.com/Dasero197/fedapay_connector/blob/main/CHANGELOG.md
Author-email: ASSOGBA Dayane <assogbadayane197@gmail.com>
Maintainer-email: ASSOGBA Dayane <assogbadayane197@gmail.com>
License: AGPL-3.0-or-later
License-File: LICENSE
Keywords: API,asynchrone,connector,fedapay,integration,paiement
Classifier: Intended Audience :: Developers
Classifier: License :: OSI Approved :: GNU Affero General Public License v3 or later (AGPLv3+)
Classifier: Operating System :: OS Independent
Classifier: Programming Language :: Python :: 3
Classifier: Topic :: Software Development :: Libraries
Classifier: Topic :: Software Development :: Libraries :: Python Modules
Requires-Python: >=3.9
Requires-Dist: aiohttp>=3.11.16
Requires-Dist: fastapi>=0.115.12
Requires-Dist: pydantic[email]>=2.0
Requires-Dist: sqlalchemy==2.0.41
Requires-Dist: uvicorn>=0.34.2
